{"is_source_file": true, "format": "Python", "description": "This file provides security-related utility functions for password hashing, verification, and role-based access control decorators for route protection in a Flask web application.", "external_files": ["flask", "werkzeug.security", "flask_jwt_extended"], "external_methods": ["generate_password_hash", "check_password_hash", "verify_jwt_in_request", "get_jwt", "jsonify"], "published": ["hash_password", "verify_password", "require_roles"], "classes": [], "methods": [{"name": "str hash_password(plain: str)", "description": "Hash a plaintext password using werkzeug security.", "scope": "", "scopeKind": ""}, {"name": "bool verify_password(plain: str, hashed: str)", "description": "Verify password against stored hash.", "scope": "", "scopeKind": ""}, {"name": "require_roles(roles: Iterable[str])", "description": "Decorator to require one of the specified roles to access a route.", "scope": "", "scopeKind": ""}, {"name": "decorator(fn)", "scope": "require_roles", "scopeKind": "function", "description": "unavailable"}, {"name": "wrapper(*args, **kwargs)", "scope": "require_roles.decorator", "scopeKind": "function", "description": "unavailable"}], "calls": ["generate_password_hash", "check_password_hash", "verify_jwt_in_request", "get_jwt", "jsonify"], "search-terms": ["security", "password hashing", "role-based access", "JWT", "flask_jwt_extended"], "state": 2, "file_id": 8, "knowledge_revision": 18, "git_revision": "", "ctags": [{"_type": "tag", "name": "decorator", "path": "/home/kavia/workspace/code-generation/edutrack-learning-management-system-185855-185874/lms_backend/app/security.py", "pattern": "/^    def decorator(fn):$/", "file": true, "language": "Python", "kind": "function", "signature": "(fn)", "scope": "require_roles", "scopeKind": "function"}, {"_type": "tag", "name": "hash_password", "path": "/home/kavia/workspace/code-generation/edutrack-learning-management-system-185855-185874/lms_backend/app/security.py", "pattern": "/^def hash_password(plain: str) -> str:$/", "language": "Python", "typeref": "typename:str", "kind": "function", "signature": "(plain: str)"}, {"_type": "tag", "name": "require_roles", "path": "/home/kavia/workspace/code-generation/edutrack-learning-management-system-185855-185874/lms_backend/app/security.py", "pattern": "/^def require_roles(roles: Iterable[str]):$/", "language": "Python", "kind": "function", "signature": "(roles: Iterable[str])"}, {"_type": "tag", "name": "verify_password", "path": "/home/kavia/workspace/code-generation/edutrack-learning-management-system-185855-185874/lms_backend/app/security.py", "pattern": "/^def verify_password(plain: str, hashed: str) -> bool:$/", "language": "Python", "typeref": "typename:bool", "kind": "function", "signature": "(plain: str, hashed: str)"}, {"_type": "tag", "name": "wrapper", "path": "/home/kavia/workspace/code-generation/edutrack-learning-management-system-185855-185874/lms_backend/app/security.py", "pattern": "/^        def wrapper(*args, **kwargs):$/", "file": true, "language": "Python", "kind": "function", "signature": "(*args, **kwargs)", "scope": "require_roles.decorator", "scopeKind": "function"}], "hash": "e980951e4856415ed26506410b571441", "format-version": 4, "code-base-name": "lms_backend", "filename": "lms_backend/app/security.py", "revision_history": [{"18": ""}]}